{
    "users": {
        "7695728173": {
            "name": "Sanjarbek",
            "xp": 4090,
            "tasks": [
                {
                    "desc": "Salom",
                    "datetime": "2026-01-07 21:01",
                    "done": false,
                    "reminded": true,
                    "priority": "high",
                    "category": "other",
                    "difficulty": 4,
                    "status": "active",
                    "createdAt": "2026-01-07 21:00",
                    "postponeCount": 0
                },
                {
                    "desc": "Erta turish",
                    "datetime": "2026-01-07 21:32",
                    "done": false,
                    "reminded": true,
                    "priority": "high",
                    "category": "study",
                    "difficulty": 5,
                    "status": "active",
                    "createdAt": "2026-01-07 21:31",
                    "postponeCount": 0
                },
                {
                    "desc": "Salomberdik",
                    "datetime": "2026-01-07 22:55",
                    "done": false,
                    "reminded": true,
                    "priority": "high",
                    "category": "other",
                    "difficulty": 4,
                    "status": "active",
                    "createdAt": "2026-01-07 22:54",
                    "postponeCount": 0
                },
                {
                    "desc": "assdasd",
                    "datetime": "2026-01-07 23:04",
                    "done": false,
                    "reminded": true,
                    "priority": "high",
                    "category": "study",
                    "difficulty": 4,
                    "status": "active",
                    "createdAt": "2026-01-07 23:03",
                    "postponeCount": 0
                },
                {
                    "desc": "saasd",
                    "datetime": "2026-01-07 23:08",
                    "done": false,
                    "reminded": true,
                    "priority": "high",
                    "category": "other",
                    "difficulty": 5,
                    "status": "active",
                    "createdAt": "2026-01-07 23:08",
                    "postponeCount": 0
                },
                {
                    "desc": "4",
                    "datetime": "2026-01-07 23:28",
                    "done": false,
                    "reminded": true,
                    "priority": "high",
                    "category": "personal",
                    "difficulty": 4,
                    "status": "active",
                    "createdAt": "2026-01-07 23:27",
                    "postponeCount": 0
                }
            ],
            "habits": [],
            "unlocked": [
                "statistics",
                "habits",
                "motivation",
                "goal_chat",
                "voice_notes",
                "ai_tips",
                "custom_themes",
                "social_sharing",
                "achievements",
                "progress_reports",
                "custom_reminders",
                "calendar",
                "notes",
                "categories"
            ],
            "blocked": false,
            "joinedAt": "2026-01-07T15:47:13.984Z",
            "settings": {
                "notifications": true,
                "language": "uz",
                "theme": "light"
            },
            "lastBonusDate": "2026-01-07",
            "state": "goal_chat",
            "integrations": [
                "apps"
            ],
            "voiceNotes": [
                {
                    "voiceId": "AwACAgIAAxkBAAPyaV6KLfNtPM--t0bDa6_wEaYf-XwAAqeSAAKUP_lKLZy3KLfN3rM4BA",
                    "time": "21:31",
                    "desc": null
                },
                {
                    "voiceId": "AwACAgIAAxkBAAMaaV6fMyjKU6oYVTEfXpkbveJGVBAAArqUAAKfsfBKUqsOvleKZoQ4BA",
                    "time": "23:01",
                    "desc": null,
                    "lastSent": "2026-01-07"
                }
            ],
            "achievements": [
                "500 XP",
                "1000 XP",
                "5 funksiya"
            ],
            "custom_reminders": [
                {
                    "desc": "Erta tongi maqsadlarni bajarish",
                    "time": "21:51",
                    "customText": "Tursangi",
                    "lastSent": "2026-01-07"
                },
                {
                    "desc": "sad",
                    "time": "22:56",
                    "customText": "scas3c",
                    "lastSent": "2026-01-07"
                },
                {
                    "desc": "kkkj",
                    "time": "22:58",
                    "customText": "kk",
                    "lastSent": "2026-01-07"
                },
                {
                    "desc": "77272",
                    "customText": "Jsj",
                    "datetime": "2026-01-07 23:30",
                    "sent": true
                }
            ],
            "notes": [
                {
                    "text": "sads"
                }
            ]
        },
        "8014950410": {
            "name": "Alibek",
            "xp": 1999999140,
            "tasks": [],
            "habits": [],
            "unlocked": [
                "ai_tips",
                "custom_themes",
                "achievements",
                "pomodoro",
                "goal_chat"
            ],
            "blocked": false,
            "joinedAt": "2026-01-07T15:55:44.142Z",
            "settings": {
                "notifications": true,
                "language": "uz",
                "theme": "dark"
            },
            "lastBonusDate": "2026-01-07",
            "integrations": [
                "apps"
            ],
            "achievements": [
                "500 XP",
                "1000 XP"
            ],
            "state": "goal_chat"
        }
    },
    "settings": {}
}